<?xml version="1.0" encoding="UTF-8"?>
<odoo>
    <data>

    <record id="res_users_library_form_view" model="ir.ui.view">
        <field name="name">res.users.form.view</field>
        <field name="model">res.users</field>
        <field name="inherit_id" ref="base.view_users_form" />
        <field name="arch" type="xml">
            <notebook position="inside">
                <page string="Library">
                    <group>
                        <field name="library_id" placeholder="Select Library" options="{'no_create': True}"/>
                    </group>
                </page>
            </notebook>
        </field>
    </record>
    
    </data>
</odoo>
